cx104305/__init__.py
cx104305/test.py
cx104305-0.0.2.dist-info/METADATA
cx104305-0.0.2.dist-info/WHEEL
cx104305-0.0.2.dist-info/licenses/LICENSE
cx104305-0.0.2.dist-info/RECORD
